README.md
setup.py
PySolidState/__init__.py
PySolidState.egg-info/PKG-INFO
PySolidState.egg-info/SOURCES.txt
PySolidState.egg-info/dependency_links.txt
PySolidState.egg-info/requires.txt
PySolidState.egg-info/top_level.txt
PySolidState/crystal_structure/__init__.py
PySolidState/crystal_structure/atom.py
PySolidState/crystal_structure/base.py
PySolidState/crystal_structure/cell.py
PySolidState/crystal_structure/crystalStructure.py
PySolidState/crystal_structure/lattice.py
PySolidState/crystal_structure/lattices.json